kolani/__init__.py
kolani/hebrew.py
kolani/lexicon.py
kolani/log.py
kolani/phonemize.py
kolani/syllables.py
kolani/utils.py
kolani/variants.py
kolani/data/rashej_tevot.json
kolani/data/special.json
kolani/data/symbols.json
kolani/expander/__init__.py
kolani/expander/dates.py
kolani/expander/dictionary.py
kolani/expander/number_names.py
kolani/expander/numbers.py
kolani/expander/time_to_word.py
kolani-0.3.7.dist-info/METADATA
kolani-0.3.7.dist-info/WHEEL
kolani-0.3.7.dist-info/licenses/LICENSE
kolani-0.3.7.dist-info/RECORD
